README.txt
setup.cfg
setup.py
testasad222/__init__.py
testasad222/datorama.py
testasad222.egg-info/PKG-INFO
testasad222.egg-info/SOURCES.txt
testasad222.egg-info/dependency_links.txt
testasad222.egg-info/top_level.txt