Metadata-Version: 1.0
Name: testasad222
Version: 0.2
Summary: Datorama Python Package
Home-page: https://github.com/datorama/python-connector-package
Author: Asaad Awesat
Author-email: asaad.awesat@datorama.com
License: MIT
Platform: UNKNOWN
